{
    "profile": "24",
    "topMatchingProfiles": {
        "0.69": [
            64
        ],
        "0.67": [
            58
        ],
        "0.65": [
            67
        ],
        "0.64": [
            56,
            89
        ],
        "0.63": [
            87,
            83
        ],
        "0.61": [
            91
        ],
        "0.59": [
            69
        ],
        "0.56": [
            90
        ],
        "0.55": [
            60,
            70,
            82
        ],
        "0.54": [
            68,
            80
        ]
    }
}