{
    "profile": "27",
    "topMatchingProfiles": {
        "0.84": [
            54
        ],
        "0.72": [
            74
        ],
        "0.67": [
            59,
            84
        ],
        "0.65": [
            90
        ],
        "0.62": [
            55,
            88
        ],
        "0.60": [
            76,
            72,
            92
        ],
        "0.59": [
            71
        ],
        "0.57": [
            65
        ],
        "0.56": [
            69
        ],
        "0.53": [
            85
        ]
    }
}